tests/__init__.py
tests/models.py
tests/settings.py
tests/test_utils.py
tests/migrations/0001_initial.py
tests/migrations/__init__.py
wagtailtestutils/__init__.py
wagtailtestutils/utils.py
wagtailtestutils/version.py
wagtailtestutils-0.1.0.dist-info/DESCRIPTION.rst
wagtailtestutils-0.1.0.dist-info/METADATA
wagtailtestutils-0.1.0.dist-info/RECORD
wagtailtestutils-0.1.0.dist-info/WHEEL
wagtailtestutils-0.1.0.dist-info/metadata.json
wagtailtestutils-0.1.0.dist-info/top_level.txt
