Metadata-Version: 2.0
Name: wagtailtestutils
Version: 0.1.0
Summary: Test utils for Wagtail sites
Home-page: https://bitbucket.org/takeflight/wagtailtestutils
Author: Tim Heap
Author-email: tim@takeflight.com.au
License: BSD License
Platform: UNKNOWN
Classifier: Environment :: Web Environment
Classifier: Intended Audience :: Developers
Classifier: Operating System :: OS Independent
Classifier: Programming Language :: Python
Classifier: Framework :: Django
Classifier: License :: OSI Approved :: BSD License
Requires-Dist: wagtail (>=1.2)
